README.rst
setup.py
uhome/__init__.py
uhome.egg-info/PKG-INFO
uhome.egg-info/SOURCES.txt
uhome.egg-info/dependency_links.txt
uhome.egg-info/requires.txt
uhome.egg-info/top_level.txt