Metadata-Version: 1.0
Name: uhome
Version: 0.1.5
Summary: Wrapper for communication with Uponor Smatrix Wave PLUS Smart Home Gateway R-167 aka U@home.
Home-page: https://github.com/almirdelkic/uhome
Author: Almir Delkic
Author-email: UNKNOWN
License: GNU GPLv3
Platform: UNKNOWN
